rotarypi/__init__.py
rotarypi/dialconfig.py
rotarypi/dialdata.py
rotarypi/rotaryreader.py
rotarypi-2.1.2.dist-info/METADATA
rotarypi-2.1.2.dist-info/WHEEL
rotarypi-2.1.2.dist-info/top_level.txt
rotarypi-2.1.2.dist-info/RECORD
