Metadata-Version: 2.1
Name: rotarypi
Version: 2.1.2
Summary: Reading the rotary dial of an old phone with a RaspberryPi
Home-page: https://gitlab.com/rotaryphone/rotarypi
Author: Martin Obrist
Author-email: dev@obrist.email
License: MIT
Project-URL: Documentation, https://rotarypi.readthedocs.io
Project-URL: Source Code, https://gitlab.com/rotaryphone/rotarypi
Project-URL: Issue Tracker, https://gitlab.com/rotaryphone/rotarypi/-/issues
Requires-Python: >=3.9, <4
Requires-Dist: RPi.GPIO
Provides-Extra: dev
Requires-Dist: twine ; extra == 'dev'
Requires-Dist: invoke ; extra == 'dev'
